cmai/__init__.py
cmai/main.py
cmai/config/__init__.py
cmai/config/settings.py
cmai/core/__init__.py
cmai/core/get_logger.py
cmai/core/normalizer.py
cmai/providers/__init__.py
cmai/providers/base.py
cmai/providers/ollama_provider.py
cmai/providers/openai_provider.py
cmai/providers/provider_factory.py
cmai/providers/zai_provider.py
cmai/utils/__init__.py
cmai/utils/git_staged_analyzer.py
cmai-0.2.3.dist-info/licenses/LICENSE
cmai-0.2.3.dist-info/METADATA
cmai-0.2.3.dist-info/WHEEL
cmai-0.2.3.dist-info/entry_points.txt
cmai-0.2.3.dist-info/top_level.txt
cmai-0.2.3.dist-info/RECORD
