Metadata-Version: 2.4
Name: cmai
Version: 0.2.3
Summary: AI Powered Commit Message Normalization Tool
Author-email: yumuzhihan <1573252900@qq.com>
Maintainer-email: yumuzhihan <1573252900@qq.com>
License: MIT
Project-URL: Homepage, https://github.com/yumuzhihan/cmai
Project-URL: Repository, https://github.com/yumuzhihan/cmai
Project-URL: Documentation, https://github.com/yumuzhihan/cmai#readme
Project-URL: Bug Tracker, https://github.com/yumuzhihan/cmai/issues
Keywords: ai,commit,git,cli,normalization
Classifier: Development Status :: 4 - Beta
Classifier: Intended Audience :: Developers
Classifier: License :: OSI Approved :: GNU Affero General Public License v3
Classifier: Operating System :: OS Independent
Classifier: Programming Language :: Python :: 3
Classifier: Programming Language :: Python :: 3.10
Classifier: Programming Language :: Python :: 3.11
Classifier: Programming Language :: Python :: 3.12
Classifier: Topic :: Software Development :: Version Control :: Git
Classifier: Topic :: Utilities
Requires-Python: >=3.10
License-File: LICENSE
Requires-Dist: click>=8.2.1
Requires-Dist: httpx[socks]>=0.28.1
Requires-Dist: pydantic>=2.11.7
Requires-Dist: pydantic-settings>=2.10.0
Provides-Extra: dev
Requires-Dist: pytest>=7.0.0; extra == "dev"
Requires-Dist: black>=23.0.0; extra == "dev"
Requires-Dist: ruff>=0.1.0; extra == "dev"
Requires-Dist: mypy>=1.0.0; extra == "dev"
Requires-Dist: pre-commit>=3.0.0; extra == "dev"
Provides-Extra: openai
Requires-Dist: openai>=1.91.0; extra == "openai"
Provides-Extra: ollama
Requires-Dist: ollama>=0.5.1; extra == "ollama"
Provides-Extra: zai
Requires-Dist: zai-sdk>=0.2.0; extra == "zai"
Provides-Extra: all-providers
Requires-Dist: openai>=1.91.0; extra == "all-providers"
Requires-Dist: ollama>=0.5.1; extra == "all-providers"
Requires-Dist: zai-sdk>=0.2.0; extra == "all-providers"
Dynamic: license-file
